<credentials ver="2">

    <device>
        <username></username>
        <password>cisco1</password>
        <enable>ena1</enable>
        <ip>10.0.52.101</ip>
        <hostname>R1</hostname>
        <rem>Login with pass only. No username set.</rem>
    </device>

    <device>
        <username></username>
        <password>cisco2</password>
        <enable>ena2</enable>
        <ip>10.0.52.102</ip>
        <hostname>R2</hostname>
        <rem>Password not set.</rem>
    </device>

    <device>
        <username>admin</username>
        <password>cisco3</password>
        <enable>ena3</enable>
        <ip>10.0.52.103</ip>
        <hostname>R3</hostname>
        <rem>User privilege 0.</rem>
    </device>

    <device>
        <username>admin</username>
        <password>cisco4</password>
        <enable></enable>
        <ip>10.0.52.104</ip>
        <hostname>R4</hostname>
        <rem>User privilege 15.</rem>
    </device>

</credentials>